{
  "tags": [],
  "disabledBlocks": {
    "info-left": [],
    "info-right": [],
    "notes-left": [],
    "notes-right": [],
    "_id": "7a7890135a0f8370c9afac71"
  },
  "spells": {
    "mode": "text",
    "prepared": [],
    "book": []
  },
  "data": "{\"isDefault\": true, \"jsonType\": \"character\", \"template\": \"default\", \"name\": {\"value\": \"Феликс Ярый\"}, \"info\": {\"charClass\": {\"name\": \"charClass\", \"label\": \"класс и уровень\", \"value\": \"Воин\"}, \"level\": {\"name\": \"level\", \"label\": \"уровень\", \"value\": 3}, \"background\": {\"name\": \"background\", \"label\": \"предыстория\", \"value\": \"Преступник\"}, \"playerName\": {\"name\": \"playerName\", \"label\": \"имя игрока\", \"value\": \"\"}, \"race\": {\"name\": \"race\", \"label\": \"раса\", \"value\": \"Человек\"}, \"alignment\": {\"name\": \"alignment\", \"label\": \"мировоззрение\", \"value\": \"Хаотично-нейтральный\"}, \"experience\": {\"name\": \"experience\", \"label\": \"опыт\", \"value\": 0}}, \"subInfo\": {\"age\": {\"name\": \"age\", \"label\": \"возраст\", \"value\": 27}, \"height\": {\"name\": \"height\", \"label\": \"рост\", \"value\": 180}, \"weight\": {\"name\": \"weight\", \"label\": \"вес\", \"value\": 82}, \"eyes\": {\"name\": \"\", \"label\": \"\", \"value\": \"\"}, \"skin\": {\"name\": \"\", \"label\": \"\", \"value\": \"\"}, \"hair\": {\"name\": \"\", \"label\": \"\", \"value\": \"\"}}, \"spellsInfo\": {\"base\": {\"name\": \"base\", \"label\": \"Базовая характеристика заклинаний\", \"value\": \"\", \"code\": \"\"}, \"save\": {\"name\": \"save\", \"label\": \"Сложность спасброска\", \"value\": \"\", \"customModifier\": \"\"}, \"mod\": {\"name\": \"mod\", \"label\": \"Бонус атаки заклинанием\", \"value\": \"\", \"customModifier\": \"\"}}, \"spells\": {}, \"spellsPact\": {}, \"proficiency\": 2, \"stats\": {\"str\": {\"name\": \"str\", \"label\": \"Сила\", \"score\": 16, \"modifier\": 3, \"check\": 0}, \"dex\": {\"name\": \"dex\", \"label\": \"Ловкость\", \"score\": 14, \"modifier\": 2, \"check\": 0}, \"con\": {\"name\": \"con\", \"label\": \"Телосложение\", \"score\": 15, \"modifier\": 2, \"check\": 0}, \"int\": {\"name\": \"int\", \"label\": \"Интеллект\", \"score\": 11, \"modifier\": 0, \"check\": 0}, \"wis\": {\"name\": \"wis\", \"label\": \"Мудрость\", \"score\": 13, \"modifier\": 1, \"check\": 0}, \"cha\": {\"name\": \"cha\", \"label\": \"Харизма\", \"score\": 9, \"modifier\": -1, \"check\": 0}}, \"saves\": {\"str\": {\"name\": \"str\", \"isProf\": true, \"bonus\": 0}, \"dex\": {\"name\": \"dex\", \"isProf\": false, \"bonus\": 0}, \"con\": {\"name\": \"con\", \"isProf\": true, \"bonus\": 0}, \"int\": {\"name\": \"int\", \"isProf\": false, \"bonus\": 0}, \"wis\": {\"name\": \"wis\", \"isProf\": false, \"bonus\": 0}, \"cha\": {\"name\": \"cha\", \"isProf\": false, \"bonus\": 0}}, \"skills\": {\"acrobatics\": {\"baseStat\": \"dex\", \"name\": \"acrobatics\", \"label\": \"Акробатика\", \"isProf\": 0}, \"investigation\": {\"baseStat\": \"int\", \"name\": \"investigation\", \"label\": \"Анализ\", \"isProf\": 0}, \"athletics\": {\"baseStat\": \"str\", \"name\": \"athletics\", \"label\": \"Атлетика\", \"isProf\": 1}, \"perception\": {\"baseStat\": \"wis\", \"name\": \"perception\", \"label\": \"Восприятие\", \"isProf\": 1}, \"survival\": {\"baseStat\": \"wis\", \"name\": \"survival\", \"label\": \"Выживание\", \"isProf\": 0}, \"performance\": {\"baseStat\": \"cha\", \"name\": \"performance\", \"label\": \"Выступление\", \"isProf\": 0}, \"intimidation\": {\"baseStat\": \"cha\", \"name\": \"intimidation\", \"label\": \"Запугивание\", \"isProf\": 0}, \"history\": {\"baseStat\": \"int\", \"name\": \"history\", \"label\": \"История\", \"isProf\": 0}, \"sleight of hand\": {\"baseStat\": \"dex\", \"name\": \"sleight of hand\", \"label\": \"Ловкость рук\", \"isProf\": 0}, \"arcana\": {\"baseStat\": \"int\", \"name\": \"arcana\", \"label\": \"Магия\", \"isProf\": 0}, \"medicine\": {\"baseStat\": \"wis\", \"name\": \"medicine\", \"label\": \"Медицина\", \"isProf\": 0}, \"deception\": {\"baseStat\": \"cha\", \"name\": \"deception\", \"label\": \"Обман\", \"isProf\": 1}, \"nature\": {\"baseStat\": \"int\", \"name\": \"nature\", \"label\": \"Природа\", \"isProf\": 0}, \"insight\": {\"baseStat\": \"wis\", \"name\": \"insight\", \"label\": \"Проницательность\", \"isProf\": 0}, \"religion\": {\"baseStat\": \"int\", \"name\": \"religion\", \"label\": \"Религия\", \"isProf\": 0}, \"stealth\": {\"baseStat\": \"dex\", \"name\": \"stealth\", \"label\": \"Скрытность\", \"isProf\": 1}, \"persuasion\": {\"baseStat\": \"cha\", \"name\": \"persuasion\", \"label\": \"Убеждение\", \"isProf\": 0}, \"animal handling\": {\"baseStat\": \"wis\", \"name\": \"animal handling\", \"label\": \"Уход за животными\", \"isProf\": 0}}, \"vitality\": {\"hp-dice-current\": {\"value\": 3}, \"hp-dice-multi\": {}, \"hp-max\": {\"value\": 28}, \"hp-current\": {\"value\": 28}, \"hp-temp\": {\"value\": 0}, \"isDying\": false, \"deathFails\": 0, \"deathSuccesses\": 0, \"ac\": {\"value\": 19}, \"speed\": {\"value\": 30}, \"hit-die\": {\"value\": \"d10\"}, \"hp-max-bonus\": {\"value\": 0}}, \"weaponsList\": [{\"id\": \"\", \"name\": {\"value\": \"Длинный меч\"}, \"mod\": {\"value\": \"\"}, \"dmg\": {\"value\": \"1к8 рубящий\"}, \"isProf\": true, \"ability\": \"str\", \"modBonus\": {\"value\": 0}, \"modCustom\": {\"value\": 0}}, {\"id\": \"\", \"name\": {\"value\": \"Метательный топорик\"}, \"mod\": {\"value\": \"\"}, \"dmg\": {\"value\": \"1к6 рубящий\"}, \"isProf\": true, \"ability\": \"str\", \"modBonus\": {\"value\": 0}, \"modCustom\": {\"value\": 0}}], \"weapons\": {}, \"text\": {\"traits\": {\"value\": {\"data\": \"<p><strong>Стиль боя: Защита:</strong> (Полный текст в разделе 'Заметки') </p><p><strong>Второе дыхание:</strong> (Полный текст в разделе 'Заметки') </p><p><strong>Всплеск действия:</strong> (Полный текст в разделе 'Заметки') </p><p><strong>Улучшенная критическая атака:</strong> (Полный текст в разделе 'Заметки') </p>\"}}, \"attacks\": {\"value\": {\"data\": {\"type\": \"doc\", \"content\": [{\"type\": \"paragraph\", \"content\": [{\"type\": \"text\", \"text\": \"Критический удар при 19-20 (архетип Чемпион)\"}]}]}}}, \"spells-level-0\": {\"value\": {\"data\": {\"type\": \"doc\", \"content\": null}}}, \"spells-level-1\": {\"value\": {\"data\": {\"type\": \"doc\", \"content\": null}}}, \"spells-level-2\": {\"value\": {\"data\": {\"type\": \"doc\", \"content\": null}}}, \"spells-level-3\": {\"value\": {\"data\": {\"type\": \"doc\", \"content\": null}}}, \"spells-level-4\": {\"value\": {\"data\": {\"type\": \"doc\", \"content\": null}}}, \"spells-level-5\": {\"value\": {\"data\": {\"type\": \"doc\", \"content\": null}}}, \"equipment\": {\"value\": {\"data\": {\"type\": \"doc\", \"content\": [{\"type\": \"paragraph\", \"content\": [{\"type\": \"text\", \"text\": \"Кольчуга\"}]}, {\"type\": \"paragraph\", \"content\": [{\"type\": \"text\", \"text\": \"Щит\"}]}, {\"type\": \"paragraph\", \"content\": [{\"type\": \"text\", \"text\": \"Длинный меч\"}]}, {\"type\": \"paragraph\", \"content\": [{\"type\": \"text\", \"text\": \"Метательный топорик (2 шт.)\"}]}, {\"type\": \"paragraph\", \"content\": [{\"type\": \"text\", \"text\": \"Рюкзак\"}]}, {\"type\": \"paragraph\", \"content\": [{\"type\": \"text\", \"text\": \"Спальный мешок\"}]}, {\"type\": \"paragraph\", \"content\": [{\"type\": \"text\", \"text\": \"Набор для готовки\"}]}, {\"type\": \"paragraph\", \"content\": [{\"type\": \"text\", \"text\": \"Трутница\"}]}, {\"type\": \"paragraph\", \"content\": [{\"type\": \"text\", \"text\": \"Факел (10 шт.)\"}]}, {\"type\": \"paragraph\", \"content\": [{\"type\": \"text\", \"text\": \"Рационы (10 дней)\"}]}, {\"type\": \"paragraph\", \"content\": [{\"type\": \"text\", \"text\": \"Бурдюк с водой\"}]}, {\"type\": \"paragraph\", \"content\": [{\"type\": \"text\", \"text\": \"Верёвка пеньковая, 50 футов\"}]}, {\"type\": \"paragraph\", \"content\": [{\"type\": \"text\", \"text\": \"Лом\"}]}, {\"type\": \"paragraph\", \"content\": [{\"type\": \"text\", \"text\": \"Тёмная обычная одежда с капюшоном\"}]}, {\"type\": \"paragraph\", \"content\": [{\"type\": \"text\", \"text\": \"Воровские инструменты\"}]}, {\"type\": \"paragraph\", \"content\": [{\"type\": \"text\", \"text\": \"Набор игральных костей\"}]}, {\"type\": \"paragraph\", \"content\": [{\"type\": \"text\", \"text\": \"Кошелёк с 15 зм\"}]}]}}, \"isHidden\": false}, \"background\": {\"value\": {\"data\": \"Феликс вырос в трущобах большого города, где рано понял: если не умеешь держать оружие и держать слово только перед собой, выживать трудно. Юношей он сбился в банду вместе с лучшим другом — они вместе проворачивали мелкие дела, деля добычу поровну и мечтая когда-нибудь выбраться из города богатыми и свободными. Всё рухнуло, когда друг сдал его страже, спасая собственную шкуру перед облавой. Феликс отсидел своё, вышел другим человеком — внешне ещё более весёлым и беспечным, чем раньше, но внутри затаившим холодную решимость однажды найти предателя. С тех пор он берётся за любую работу, где можно заработать и почувствовать себя свободным: сопровождает караваны, охраняет лавки, влезает в чужие авантюры — лишь бы не сидеть на месте. Любопытство тянет его в подземелья и заброшенные дома, но есть вещи, которые даже он обходит стороной: непроглядная темнота и бродячие клоунские труппы вызывают у него неконтролируемую дрожь, о которой он никому не рассказывает.\"}}, \"ideals\": {\"value\": {\"data\": \"Свобода. Никакие цепи, законы и чужие правила не указывают мне, за что браться, а звонкая монета всегда открывает больше дверей, чем чужое одобрение.\"}}, \"personality\": {\"value\": {\"data\": \"Даже в разгар передряги я не могу удержаться от шутки — смех глушит собственный страх лучше любого щита.\"}}, \"flaws\": {\"value\": {\"data\": \"Я до дрожи боюсь темноты и клоунов, и скорее совру с три короба, чем признаюсь в этом при свидетелях.\"}}, \"bonds\": {\"value\": {\"data\": \"Я поклялся однажды рассчитаться с бывшим лучшим другом, который сдал меня страже ради собственной выгоды — и который всё ещё где-то в этом городе.\"}}, \"allies\": {\"value\": {\"data\": \"\"}}, \"quests\": {\"value\": {\"data\": \"\"}}, \"prof\": {\"value\": {\"data\": \"<p><strong>Знание языков:</strong> Общий, Воровской жаргон</p><p><strong>Сопротивление к:</strong> Нет</p><p><strong>Доспехи:</strong> Любые доспехи, Щиты</p><p><strong>Оружие:</strong> Простое оружие, Воинское оружие</p><p><strong>Инструменты от класса: </strong> Воровские инструменты, Набор игральных костей</p><p><strong>Инструменты от предыстории: </strong> Нет</p>\"}}, \"notes-1\": {\"value\": {\"data\": \"<strong>Умения от класса:</strong> <p><strong>Стиль боя: Защита:</strong> Пока вы носите доспехи, вы получаете +1 к КД.</p><p><strong>Второе дыхание:</strong> Бонусным действием, один раз между отдыхами, вы восстанавливаете 1к10+3 хитов.</p><p><strong>Всплеск действия:</strong> Один раз между отдыхами вы можете совершить одно дополнительное действие в свой ход.</p>\"}}, \"notes-2\": {\"value\": {\"data\": \"<strong>Умения от класса:</strong> <p><strong>Улучшенная критическая атака:</strong> Ваши атаки оружием наносят критический удар при выпадении 19 или 20 на кубике атаки.</p>\"}}, \"notes-3\": {\"value\": {\"data\": \"\"}}, \"notes-4\": {\"value\": {\"data\": \"<p><strong>Умения от расы:</strong> <p><strong>Универсальность:</strong> Один дополнительный язык на выбор.</p></p>\"}}, \"notes-5\": {\"value\": {\"data\": \"<p><strong>Умения от черт:</strong> Нет</p>\"}}, \"notes-6\": {\"value\": {\"data\": \"\"}}, \"features\": {\"value\": {\"data\": {\"type\": \"doc\", \"content\": [{\"type\": \"paragraph\", \"content\": [{\"type\": \"text\", \"text\": \"Криминальный контакт:\"}]}, {\"type\": \"paragraph\", \"content\": [{\"type\": \"text\", \"text\": \"У вас есть надёжный контакт среди преступного мира, который может передавать вам сведения и помогать со связями за услуги или деньги.\"}]}]}}}, \"items\": {\"value\": {\"data\": \"\"}}}, \"coins\": {\"gp\": {\"value\": 15}, \"total\": {\"value\": 15}, \"sp\": {\"value\": 0}, \"cp\": {\"value\": 0}, \"pp\": {\"value\": 0}, \"ep\": {\"value\": 0}}, \"resources\": {}, \"bonusesSkills\": null, \"bonusesStats\": null, \"conditions\": null, \"hiddenName\": \"Феликс Ярый\", \"casterClass\": {\"value\": \"Воин\"}, \"avatar\": {\"jpeg\": \"\", \"webp\": \"\"}, \"inspiration\": false, \"exhaustion\": \"\", \"createdAt\": \"2026-07-14T11:24:40Z\", \"proficiencyCustom\": 0}",
  "edition": "2014",
  "jsonType": "character",
  "version": "2"
}